{
    "configen": {
        "version": "4",
        "sources": [
            {
                "id": "lib",
                "path": "src/main/golang",
                "r": true
            },
            {
                "id": "test",
                "path": "src/test/golang",
                "r": true
            }
        ],
        "destinations": [
            {
                "id": "lib",
                "path": "gen/lib4libredis",
                "sources": [
                    "lib"
                ]
            },
            {
                "id": "test",
                "path": "gen/test4libredis",
                "sources": [
                    "test"
                ]
            }
        ]
    }
}